typeunions/__init__.py
typeunions/typeunion.py
typeunions-0.0.1.dist-info/METADATA
typeunions-0.0.1.dist-info/WHEEL
typeunions-0.0.1.dist-info/licenses/LICENSE
typeunions-0.0.1.dist-info/RECORD
