Metadata-Version: 2.1
Name: typeunions
Version: 0.0.1
Summary: type unions
Project-URL: Homepage, https://github.com/bajacc/typeunions
Project-URL: Issues, https://github.com/bajacc/typeunions/issues
Author-email: bajacc <baptiste.jacquemot@gmail.com>
License-File: LICENSE
Classifier: License :: OSI Approved :: MIT License
Classifier: Operating System :: OS Independent
Classifier: Programming Language :: Python :: 3
Requires-Python: >=3.10
